regtest/__init__.py
regtest/regtest.py
regtest-0.1.dist-info/LICENSE
regtest-0.1.dist-info/METADATA
regtest-0.1.dist-info/WHEEL
regtest-0.1.dist-info/top_level.txt
regtest-0.1.dist-info/RECORD
