Metadata-Version: 2.1
Name: regtest
Version: 0.1
Summary: regression test enhancement for the Python unittest framework.
Home-page: https://github.com/sonntagsgesicht/regtest
Author: sonntagsgesicht
Author-email: sonntagsgesicht@icloud.com
License: Apache License 2.0
Platform: any
Classifier: Development Status :: 4 - Beta
Classifier: Intended Audience :: Education
Classifier: Intended Audience :: Developers
Classifier: License :: OSI Approved :: Apache Software License
Classifier: Operating System :: OS Independent
Classifier: Programming Language :: Python
Classifier: Programming Language :: Python :: 2
Classifier: Programming Language :: Python :: 2.7
Classifier: Programming Language :: Python :: 3
Classifier: Programming Language :: Python :: 3.5
Classifier: Programming Language :: Python :: 3.6
Classifier: Programming Language :: Python :: 3.7
Classifier: Topic :: Education
Classifier: Topic :: Software Development
